{
  "errors": "Sorry, something went wrong.",
  "message": "Class 'App\\Utils\\EmployeeTool' not found",
  "trace": [
    {
      "function": "create",
      "class": "App\\Http\\Controllers\\Api\\V1\\Client\\EmployeeController",
      "type": "->",
      "args": [
        {
          "attributes": {},
          "request": {},
          "query": {},
          "server": {},
          "files": {},
          "cookies": {},
          "headers": {}
        },
        {}
      ]
    },
    {
      "file": "\/home\/sandboxwotc\/laravel\/vendor\/laravel\/framework\/src\/Illuminate\/Routing\/Controller.php",
      "line": 54,
      "function": "call_user_func_array",
      "args": [
        [
          {},
          "create"
        ],
        [
          {
            "attributes": {},
            "request": {},
            "query": {},
            "server": {},
            "files": {},
            "cookies": {},
            "headers": {}
          },
          {}
        ]
      ]
    },
    {
      "file": "\/home\/sandboxwotc\/laravel\/vendor\/laravel\/framework\/src\/Illuminate\/Routing\/ControllerDispatcher.php",
      "line": 45,
      "function": "callAction",
      "class": "Illuminate\\Routing\\Controller",
      "type": "->",
      "args": [
        "create",
        [
          {
            "attributes": {},
            "request": {},
            "query": {},
            "server": {},
            "files": {},
            "cookies": {},
            "headers": {}
          },
          {}
        ]
      ]
    },
    {
      "file": "\/home\/sandboxwotc\/laravel\/vendor\/laravel\/framework\/src\/Illuminate\/Routing\/Route.php",
      "line": 212,
      "function": "dispatch",
      "class": "Illuminate\\Routing\\ControllerDispatcher",
      "type": "->",
      "args": [
        {
          "uri": "api\/v1\/employees",
          "methods": [
            "POST"
          ],
          "action": {
            "middleware": [
              "api",
              "auth:api"
            ],
            "uses": "App\\Http\\Controllers\\Api\\V1\\Client\\EmployeeController@create",
            "controller": "App\\Http\\Controllers\\Api\\V1\\Client\\EmployeeController@create",
            "namespace": "App\\Http\\Controllers\\Api\\V1",
            "prefix": "api\/v1",
            "where": [],
            "as": "api.v1.employees.create"
          },
          "isFallback": false,
          "controller": {},
          "defaults": [],
          "wheres": [],
          "parameters": [],
          "parameterNames": [],
          "computedMiddleware": [
            "api",
            "auth:api"
          ],
          "compiled": {}
        },
        {},
        "create"
      ]
    },
    {
      "file": "\/home\/sandboxwotc\/laravel\/vendor\/laravel\/framework\/src\/Illuminate\/Routing\/Route.php",
      "line": 169,
      "function": "runController",
      "class": "Illuminate\\Routing\\Route",
      "type": "->",
      "args": []
    },
    {
      "file": "\/home\/sandboxwotc\/laravel\/vendor\/laravel\/framework\/src\/Illuminate\/Routing\/Router.php",
      "line": 679,
      "function": "run",
      "class": "Illuminate\\Routing\\Route",
      "type": "->",
      "args": []
    },
    {
      "file": "\/home\/sandboxwotc\/laravel\/vendor\/laravel\/framework\/src\/Illuminate\/Routing\/Pipeline.php",
      "line": 30,
      "function": "Illuminate\\Routing\\{closure}",
      "class": "Illuminate\\Routing\\Router",
      "type": "->",
      "args": [
        {
          "attributes": {},
          "request": {},
          "query": {},
          "server": {},
          "files": {},
          "cookies": {},
          "headers": {}
        }
      ]
    },
    {
      "file": "\/home\/sandboxwotc\/laravel\/vendor\/laravel\/framework\/src\/Illuminate\/Routing\/Middleware\/SubstituteBindings.php",
      "line": 41,
      "function": "Illuminate\\Routing\\{closure}",
      "class": "Illuminate\\Routing\\Pipeline",
      "type": "->",
      "args": [
        {
          "attributes": {},
          "request": {},
          "query": {},
          "server": {},
          "files": {},
          "cookies": {},
          "headers": {}
        }
      ]
    },
    {
      "file": "\/home\/sandboxwotc\/laravel\/vendor\/laravel\/framework\/src\/Illuminate\/Pipeline\/Pipeline.php",
      "line": 151,
      "function": "handle",
      "class": "Illuminate\\Routing\\Middleware\\SubstituteBindings",
      "type": "->",
      "args": [
        {
          "attributes": {},
          "request": {},
          "query": {},
          "server": {},
          "files": {},
          "cookies": {},
          "headers": {}
        },
        {}
      ]
    },
    {
      "file": "\/home\/sandboxwotc\/laravel\/vendor\/laravel\/framework\/src\/Illuminate\/Routing\/Pipeline.php",
      "line": 53,
      "function": "Illuminate\\Pipeline\\{closure}",
      "class": "Illuminate\\Pipeline\\Pipeline",
      "type": "->",
      "args": [
        {
          "attributes": {},
          "request": {},
          "query": {},
          "server": {},
          "files": {},
          "cookies": {},
          "headers": {}
        }
      ]
    },
    {
      "file": "\/home\/sandboxwotc\/laravel\/vendor\/laravel\/framework\/src\/Illuminate\/Auth\/Middleware\/Authenticate.php",
      "line": 43,
      "function": "Illuminate\\Routing\\{closure}",
      "class": "Illuminate\\Routing\\Pipeline",
      "type": "->",
      "args": [
        {
          "attributes": {},
          "request": {},
          "query": {},
          "server": {},
          "files": {},
          "cookies": {},
          "headers": {}
        }
      ]
    },
    {
      "file": "\/home\/sandboxwotc\/laravel\/vendor\/laravel\/framework\/src\/Illuminate\/Pipeline\/Pipeline.php",
      "line": 151,
      "function": "handle",
      "class": "Illuminate\\Auth\\Middleware\\Authenticate",
      "type": "->",
      "args": [
        {
          "attributes": {},
          "request": {},
          "query": {},
          "server": {},
          "files": {},
          "cookies": {},
          "headers": {}
        },
        {},
        "api"
      ]
    },
    {
      "file": "\/home\/sandboxwotc\/laravel\/vendor\/laravel\/framework\/src\/Illuminate\/Routing\/Pipeline.php",
      "line": 53,
      "function": "Illuminate\\Pipeline\\{closure}",
      "class": "Illuminate\\Pipeline\\Pipeline",
      "type": "->",
      "args": [
        {
          "attributes": {},
          "request": {},
          "query": {},
          "server": {},
          "files": {},
          "cookies": {},
          "headers": {}
        }
      ]
    },
    {
      "file": "\/home\/sandboxwotc\/laravel\/vendor\/laravel\/framework\/src\/Illuminate\/Routing\/Middleware\/ThrottleRequests.php",
      "line": 58,
      "function": "Illuminate\\Routing\\{closure}",
      "class": "Illuminate\\Routing\\Pipeline",
      "type": "->",
      "args": [
        {
          "attributes": {},
          "request": {},
          "query": {},
          "server": {},
          "files": {},
          "cookies": {},
          "headers": {}
        }
      ]
    },
    {
      "file": "\/home\/sandboxwotc\/laravel\/vendor\/laravel\/framework\/src\/Illuminate\/Pipeline\/Pipeline.php",
      "line": 151,
      "function": "handle",
      "class": "Illuminate\\Routing\\Middleware\\ThrottleRequests",
      "type": "->",
      "args": [
        {
          "attributes": {},
          "request": {},
          "query": {},
          "server": {},
          "files": {},
          "cookies": {},
          "headers": {}
        },
        {},
        60,
        "1"
      ]
    },
    {
      "file": "\/home\/sandboxwotc\/laravel\/vendor\/laravel\/framework\/src\/Illuminate\/Routing\/Pipeline.php",
      "line": 53,
      "function": "Illuminate\\Pipeline\\{closure}",
      "class": "Illuminate\\Pipeline\\Pipeline",
      "type": "->",
      "args": [
        {
          "attributes": {},
          "request": {},
          "query": {},
          "server": {},
          "files": {},
          "cookies": {},
          "headers": {}
        }
      ]
    },
    {
      "file": "\/home\/sandboxwotc\/laravel\/vendor\/laravel\/framework\/src\/Illuminate\/Pipeline\/Pipeline.php",
      "line": 104,
      "function": "Illuminate\\Routing\\{closure}",
      "class": "Illuminate\\Routing\\Pipeline",
      "type": "->",
      "args": [
        {
          "attributes": {},
          "request": {},
          "query": {},
          "server": {},
          "files": {},
          "cookies": {},
          "headers": {}
        }
      ]
    },
    {
      "file": "\/home\/sandboxwotc\/laravel\/vendor\/laravel\/framework\/src\/Illuminate\/Routing\/Router.php",
      "line": 681,
      "function": "then",
      "class": "Illuminate\\Pipeline\\Pipeline",
      "type": "->",
      "args": [
        {}
      ]
    },
    {
      "file": "\/home\/sandboxwotc\/laravel\/vendor\/laravel\/framework\/src\/Illuminate\/Routing\/Router.php",
      "line": 656,
      "function": "runRouteWithinStack",
      "class": "Illuminate\\Routing\\Router",
      "type": "->",
      "args": [
        {
          "uri": "api\/v1\/employees",
          "methods": [
            "POST"
          ],
          "action": {
            "middleware": [
              "api",
              "auth:api"
            ],
            "uses": "App\\Http\\Controllers\\Api\\V1\\Client\\EmployeeController@create",
            "controller": "App\\Http\\Controllers\\Api\\V1\\Client\\EmployeeController@create",
            "namespace": "App\\Http\\Controllers\\Api\\V1",
            "prefix": "api\/v1",
            "where": [],
            "as": "api.v1.employees.create"
          },
          "isFallback": false,
          "controller": {},
          "defaults": [],
          "wheres": [],
          "parameters": [],
          "parameterNames": [],
          "computedMiddleware": [
            "api",
            "auth:api"
          ],
          "compiled": {}
        },
        {
          "attributes": {},
          "request": {},
          "query": {},
          "server": {},
          "files": {},
          "cookies": {},
          "headers": {}
        }
      ]
    },
    {
      "file": "\/home\/sandboxwotc\/laravel\/vendor\/laravel\/framework\/src\/Illuminate\/Routing\/Router.php",
      "line": 622,
      "function": "runRoute",
      "class": "Illuminate\\Routing\\Router",
      "type": "->",
      "args": [
        {
          "attributes": {},
          "request": {},
          "query": {},
          "server": {},
          "files": {},
          "cookies": {},
          "headers": {}
        },
        {
          "uri": "api\/v1\/employees",
          "methods": [
            "POST"
          ],
          "action": {
            "middleware": [
              "api",
              "auth:api"
            ],
            "uses": "App\\Http\\Controllers\\Api\\V1\\Client\\EmployeeController@create",
            "controller": "App\\Http\\Controllers\\Api\\V1\\Client\\EmployeeController@create",
            "namespace": "App\\Http\\Controllers\\Api\\V1",
            "prefix": "api\/v1",
            "where": [],
            "as": "api.v1.employees.create"
          },
          "isFallback": false,
          "controller": {},
          "defaults": [],
          "wheres": [],
          "parameters": [],
          "parameterNames": [],
          "computedMiddleware": [
            "api",
            "auth:api"
          ],
          "compiled": {}
        }
      ]
    },
    {
      "file": "\/home\/sandboxwotc\/laravel\/vendor\/laravel\/framework\/src\/Illuminate\/Routing\/Router.php",
      "line": 611,
      "function": "dispatchToRoute",
      "class": "Illuminate\\Routing\\Router",
      "type": "->",
      "args": [
        {
          "attributes": {},
          "request": {},
          "query": {},
          "server": {},
          "files": {},
          "cookies": {},
          "headers": {}
        }
      ]
    },
    {
      "file": "\/home\/sandboxwotc\/laravel\/vendor\/laravel\/framework\/src\/Illuminate\/Foundation\/Http\/Kernel.php",
      "line": 176,
      "function": "dispatch",
      "class": "Illuminate\\Routing\\Router",
      "type": "->",
      "args": [
        {
          "attributes": {},
          "request": {},
          "query": {},
          "server": {},
          "files": {},
          "cookies": {},
          "headers": {}
        }
      ]
    },
    {
      "file": "\/home\/sandboxwotc\/laravel\/vendor\/laravel\/framework\/src\/Illuminate\/Routing\/Pipeline.php",
      "line": 30,
      "function": "Illuminate\\Foundation\\Http\\{closure}",
      "class": "Illuminate\\Foundation\\Http\\Kernel",
      "type": "->",
      "args": [
        {
          "attributes": {},
          "request": {},
          "query": {},
          "server": {},
          "files": {},
          "cookies": {},
          "headers": {}
        }
      ]
    },
    {
      "file": "\/home\/sandboxwotc\/laravel\/vendor\/barryvdh\/laravel-debugbar\/src\/Middleware\/InjectDebugbar.php",
      "line": 58,
      "function": "Illuminate\\Routing\\{closure}",
      "class": "Illuminate\\Routing\\Pipeline",
      "type": "->",
      "args": [
        {
          "attributes": {},
          "request": {},
          "query": {},
          "server": {},
          "files": {},
          "cookies": {},
          "headers": {}
        }
      ]
    },
    {
      "file": "\/home\/sandboxwotc\/laravel\/vendor\/laravel\/framework\/src\/Illuminate\/Pipeline\/Pipeline.php",
      "line": 151,
      "function": "handle",
      "class": "Barryvdh\\Debugbar\\Middleware\\InjectDebugbar",
      "type": "->",
      "args": [
        {
          "attributes": {},
          "request": {},
          "query": {},
          "server": {},
          "files": {},
          "cookies": {},
          "headers": {}
        },
        {}
      ]
    },
    {
      "file": "\/home\/sandboxwotc\/laravel\/vendor\/laravel\/framework\/src\/Illuminate\/Routing\/Pipeline.php",
      "line": 53,
      "function": "Illuminate\\Pipeline\\{closure}",
      "class": "Illuminate\\Pipeline\\Pipeline",
      "type": "->",
      "args": [
        {
          "attributes": {},
          "request": {},
          "query": {},
          "server": {},
          "files": {},
          "cookies": {},
          "headers": {}
        }
      ]
    },
    {
      "file": "\/home\/sandboxwotc\/laravel\/app\/Http\/Middleware\/ClearCache.php",
      "line": 38,
      "function": "Illuminate\\Routing\\{closure}",
      "class": "Illuminate\\Routing\\Pipeline",
      "type": "->",
      "args": [
        {
          "attributes": {},
          "request": {},
          "query": {},
          "server": {},
          "files": {},
          "cookies": {},
          "headers": {}
        }
      ]
    },
    {
      "file": "\/home\/sandboxwotc\/laravel\/vendor\/laravel\/framework\/src\/Illuminate\/Pipeline\/Pipeline.php",
      "line": 151,
      "function": "handle",
      "class": "App\\Http\\Middleware\\ClearCache",
      "type": "->",
      "args": [
        {
          "attributes": {},
          "request": {},
          "query": {},
          "server": {},
          "files": {},
          "cookies": {},
          "headers": {}
        },
        {}
      ]
    },
    {
      "file": "\/home\/sandboxwotc\/laravel\/vendor\/laravel\/framework\/src\/Illuminate\/Routing\/Pipeline.php",
      "line": 53,
      "function": "Illuminate\\Pipeline\\{closure}",
      "class": "Illuminate\\Pipeline\\Pipeline",
      "type": "->",
      "args": [
        {
          "attributes": {},
          "request": {},
          "query": {},
          "server": {},
          "files": {},
          "cookies": {},
          "headers": {}
        }
      ]
    },
    {
      "file": "\/home\/sandboxwotc\/laravel\/vendor\/laravel\/framework\/src\/Illuminate\/Foundation\/Http\/Middleware\/TransformsRequest.php",
      "line": 31,
      "function": "Illuminate\\Routing\\{closure}",
      "class": "Illuminate\\Routing\\Pipeline",
      "type": "->",
      "args": [
        {
          "attributes": {},
          "request": {},
          "query": {},
          "server": {},
          "files": {},
          "cookies": {},
          "headers": {}
        }
      ]
    },
    {
      "file": "\/home\/sandboxwotc\/laravel\/vendor\/laravel\/framework\/src\/Illuminate\/Pipeline\/Pipeline.php",
      "line": 151,
      "function": "handle",
      "class": "Illuminate\\Foundation\\Http\\Middleware\\TransformsRequest",
      "type": "->",
      "args": [
        {
          "attributes": {},
          "request": {},
          "query": {},
          "server": {},
          "files": {},
          "cookies": {},
          "headers": {}
        },
        {}
      ]
    },
    {
      "file": "\/home\/sandboxwotc\/laravel\/vendor\/laravel\/framework\/src\/Illuminate\/Routing\/Pipeline.php",
      "line": 53,
      "function": "Illuminate\\Pipeline\\{closure}",
      "class": "Illuminate\\Pipeline\\Pipeline",
      "type": "->",
      "args": [
        {
          "attributes": {},
          "request": {},
          "query": {},
          "server": {},
          "files": {},
          "cookies": {},
          "headers": {}
        }
      ]
    },
    {
      "file": "\/home\/sandboxwotc\/laravel\/vendor\/laravel\/framework\/src\/Illuminate\/Foundation\/Http\/Middleware\/ValidatePostSize.php",
      "line": 27,
      "function": "Illuminate\\Routing\\{closure}",
      "class": "Illuminate\\Routing\\Pipeline",
      "type": "->",
      "args": [
        {
          "attributes": {},
          "request": {},
          "query": {},
          "server": {},
          "files": {},
          "cookies": {},
          "headers": {}
        }
      ]
    },
    {
      "file": "\/home\/sandboxwotc\/laravel\/vendor\/laravel\/framework\/src\/Illuminate\/Pipeline\/Pipeline.php",
      "line": 151,
      "function": "handle",
      "class": "Illuminate\\Foundation\\Http\\Middleware\\ValidatePostSize",
      "type": "->",
      "args": [
        {
          "attributes": {},
          "request": {},
          "query": {},
          "server": {},
          "files": {},
          "cookies": {},
          "headers": {}
        },
        {}
      ]
    },
    {
      "file": "\/home\/sandboxwotc\/laravel\/vendor\/laravel\/framework\/src\/Illuminate\/Routing\/Pipeline.php",
      "line": 53,
      "function": "Illuminate\\Pipeline\\{closure}",
      "class": "Illuminate\\Pipeline\\Pipeline",
      "type": "->",
      "args": [
        {
          "attributes": {},
          "request": {},
          "query": {},
          "server": {},
          "files": {},
          "cookies": {},
          "headers": {}
        }
      ]
    },
    {
      "file": "\/home\/sandboxwotc\/laravel\/vendor\/laravel\/framework\/src\/Illuminate\/Foundation\/Http\/Middleware\/CheckForMaintenanceMode.php",
      "line": 62,
      "function": "Illuminate\\Routing\\{closure}",
      "class": "Illuminate\\Routing\\Pipeline",
      "type": "->",
      "args": [
        {
          "attributes": {},
          "request": {},
          "query": {},
          "server": {},
          "files": {},
          "cookies": {},
          "headers": {}
        }
      ]
    },
    {
      "file": "\/home\/sandboxwotc\/laravel\/vendor\/laravel\/framework\/src\/Illuminate\/Pipeline\/Pipeline.php",
      "line": 151,
      "function": "handle",
      "class": "Illuminate\\Foundation\\Http\\Middleware\\CheckForMaintenanceMode",
      "type": "->",
      "args": [
        {
          "attributes": {},
          "request": {},
          "query": {},
          "server": {},
          "files": {},
          "cookies": {},
          "headers": {}
        },
        {}
      ]
    },
    {
      "file": "\/home\/sandboxwotc\/laravel\/vendor\/laravel\/framework\/src\/Illuminate\/Routing\/Pipeline.php",
      "line": 53,
      "function": "Illuminate\\Pipeline\\{closure}",
      "class": "Illuminate\\Pipeline\\Pipeline",
      "type": "->",
      "args": [
        {
          "attributes": {},
          "request": {},
          "query": {},
          "server": {},
          "files": {},
          "cookies": {},
          "headers": {}
        }
      ]
    },
    {
      "file": "\/home\/sandboxwotc\/laravel\/vendor\/laravel\/framework\/src\/Illuminate\/Pipeline\/Pipeline.php",
      "line": 104,
      "function": "Illuminate\\Routing\\{closure}",
      "class": "Illuminate\\Routing\\Pipeline",
      "type": "->",
      "args": [
        {
          "attributes": {},
          "request": {},
          "query": {},
          "server": {},
          "files": {},
          "cookies": {},
          "headers": {}
        }
      ]
    },
    {
      "file": "\/home\/sandboxwotc\/laravel\/vendor\/laravel\/framework\/src\/Illuminate\/Foundation\/Http\/Kernel.php",
      "line": 151,
      "function": "then",
      "class": "Illuminate\\Pipeline\\Pipeline",
      "type": "->",
      "args": [
        {}
      ]
    },
    {
      "file": "\/home\/sandboxwotc\/laravel\/vendor\/laravel\/framework\/src\/Illuminate\/Foundation\/Http\/Kernel.php",
      "line": 116,
      "function": "sendRequestThroughRouter",
      "class": "Illuminate\\Foundation\\Http\\Kernel",
      "type": "->",
      "args": [
        {
          "attributes": {},
          "request": {},
          "query": {},
          "server": {},
          "files": {},
          "cookies": {},
          "headers": {}
        }
      ]
    },
    {
      "file": "\/home\/sandboxwotc\/public_html\/portal\/index.php",
      "line": 55,
      "function": "handle",
      "class": "Illuminate\\Foundation\\Http\\Kernel",
      "type": "->",
      "args": [
        {
          "attributes": {},
          "request": {},
          "query": {},
          "server": {},
          "files": {},
          "cookies": {},
          "headers": {}
        }
      ]
    }
  ]
}